{
    "name": "Edge Orientation Pointing To Concave Corner",
    "tree": {
        "bl_idname": "GeometryNodeTree",
        "name": "Edge Orientation Pointing To Concave Corner",
        "uuid": "45821bb4-af42-423a-8582-808de4bb2137",
        "nodes": {
            "Group Output": {
                "bl_idname": "NodeGroupOutput",
                "location": [
                    579.698974609375,
                    -11.953693389892578
                ],
                "name": "Group Output",
                "inputs": [
                    {
                        "bl_idname": "NodeSocketVector",
                        "default_value": [
                            0.0,
                            0.0,
                            0.0
                        ],
                        "index": 0
                    },
                    {
                        "bl_idname": "NodeSocketVector",
                        "default_value": [
                            0.0,
                            0.0,
                            0.0
                        ],
                        "index": 1
                    }
                ]
            },
            "Group Input": {
                "bl_idname": "NodeGroupInput",
                "location": [
                    -839.2509765625,
                    -31.661945343017578
                ],
                "name": "Group Input",
                "outputs": [
                    {
                        "bl_idname": "NodeSocketGeometry",
                        "to_socket_index": [
                            0,
                            0,
                            1,
                            0
                        ],
                        "to_node": [
                            "Group",
                            "Group.005",
                            "Group.006",
                            "Group.002"
                        ],
                        "index": 0
                    },
                    {
                        "bl_idname": "NodeSocketInt",
                        "to_socket_index": [
                            2,
                            1
                        ],
                        "to_node": [
                            "Group.006",
                            "Group.002"
                        ],
                        "index": 1
                    }
                ]
            },
            "Group": {
                "bl_idname": "GeometryNodeGroup",
                "location": [
                    -123.92601776123047,
                    -7.214067459106445
                ],
                "name": "Group",
                "node_tree": "15ae2f7c-9360-4c97-abfe-b0f397170443",
                "outputs": [
                    {
                        "bl_idname": "NodeSocketVector",
                        "default_value": [
                            0.0,
                            0.0,
                            0.0
                        ],
                        "to_socket_index": [
                            1
                        ],
                        "to_node": [
                            "Vector Math.004"
                        ],
                        "index": 0
                    }
                ]
            },
            "Group.005": {
                "bl_idname": "GeometryNodeGroup",
                "location": [
                    -127.37281036376953,
                    -162.4652862548828
                ],
                "name": "Group.005",
                "node_tree": "15ae2f7c-9360-4c97-abfe-b0f397170443",
                "outputs": [
                    {
                        "bl_idname": "NodeSocketVector",
                        "default_value": [
                            0.0,
                            0.0,
                            0.0
                        ],
                        "to_socket_index": [
                            1
                        ],
                        "to_node": [
                            "Vector Math.005"
                        ],
                        "index": 0
                    }
                ]
            },
            "Group.006": {
                "bl_idname": "GeometryNodeGroup",
                "location": [
                    -392.3415222167969,
                    76.36473846435547
                ],
                "name": "Group.006",
                "node_tree": "ce22a211-0f15-4114-8f92-223439897968",
                "inputs": [
                    {
                        "bl_idname": "NodeSocketMenu",
                        "default_value": "Mesh",
                        "index": 0
                    }
                ],
                "outputs": [
                    {
                        "bl_idname": "NodeSocketInt",
                        "to_socket_index": [
                            1
                        ],
                        "to_node": [
                            "Group"
                        ],
                        "index": 0
                    },
                    {
                        "bl_idname": "NodeSocketInt",
                        "to_socket_index": [
                            1
                        ],
                        "to_node": [
                            "Group.005"
                        ],
                        "index": 1
                    }
                ]
            },
            "Vector Math.004": {
                "bl_idname": "ShaderNodeVectorMath",
                "location": [
                    169.698974609375,
                    75.0668716430664
                ],
                "name": "Vector Math.004",
                "operation": "SUBTRACT",
                "inputs": [
                    {
                        "bl_idname": "NodeSocketVector",
                        "default_value": [
                            0.0,
                            0.0,
                            0.0
                        ],
                        "index": 0
                    },
                    {
                        "bl_idname": "NodeSocketVector",
                        "default_value": [
                            0.0,
                            0.0,
                            0.0
                        ],
                        "index": 1
                    },
                    {
                        "bl_idname": "NodeSocketVector",
                        "default_value": [
                            0.0,
                            0.0,
                            0.0
                        ],
                        "index": 2
                    },
                    {
                        "bl_idname": "NodeSocketFloat",
                        "default_value": 1.0,
                        "index": 3
                    }
                ],
                "outputs": [
                    {
                        "bl_idname": "NodeSocketVector",
                        "default_value": [
                            0.0,
                            0.0,
                            0.0
                        ],
                        "to_socket_index": [
                            0
                        ],
                        "to_node": [
                            "Vector Math.006"
                        ],
                        "index": 0
                    }
                ]
            },
            "Group.002": {
                "bl_idname": "GeometryNodeGroup",
                "location": [
                    -215.60354614257812,
                    276.6627502441406
                ],
                "name": "Group.002",
                "node_tree": "15ae2f7c-9360-4c97-abfe-b0f397170443",
                "outputs": [
                    {
                        "bl_idname": "NodeSocketVector",
                        "default_value": [
                            0.0,
                            0.0,
                            0.0
                        ],
                        "to_socket_index": [
                            0,
                            0
                        ],
                        "to_node": [
                            "Vector Math.005",
                            "Vector Math.004"
                        ],
                        "index": 0
                    }
                ]
            },
            "Vector Math.005": {
                "bl_idname": "ShaderNodeVectorMath",
                "location": [
                    169.698974609375,
                    -144.93312072753906
                ],
                "name": "Vector Math.005",
                "operation": "SUBTRACT",
                "inputs": [
                    {
                        "bl_idname": "NodeSocketVector",
                        "default_value": [
                            0.0,
                            0.0,
                            0.0
                        ],
                        "index": 0
                    },
                    {
                        "bl_idname": "NodeSocketVector",
                        "default_value": [
                            0.0,
                            0.0,
                            0.0
                        ],
                        "index": 1
                    },
                    {
                        "bl_idname": "NodeSocketVector",
                        "default_value": [
                            0.0,
                            0.0,
                            0.0
                        ],
                        "index": 2
                    },
                    {
                        "bl_idname": "NodeSocketFloat",
                        "default_value": 1.0,
                        "index": 3
                    }
                ],
                "outputs": [
                    {
                        "bl_idname": "NodeSocketVector",
                        "default_value": [
                            0.0,
                            0.0,
                            0.0
                        ],
                        "to_socket_index": [
                            0
                        ],
                        "to_node": [
                            "Vector Math.007"
                        ],
                        "index": 0
                    }
                ]
            },
            "Vector Math.006": {
                "bl_idname": "ShaderNodeVectorMath",
                "location": [
                    389.698974609375,
                    75.0668716430664
                ],
                "name": "Vector Math.006",
                "operation": "NORMALIZE",
                "inputs": [
                    {
                        "bl_idname": "NodeSocketVector",
                        "default_value": [
                            0.0,
                            0.0,
                            0.0
                        ],
                        "index": 0
                    },
                    {
                        "bl_idname": "NodeSocketVector",
                        "default_value": [
                            0.0,
                            0.0,
                            0.0
                        ],
                        "index": 1
                    },
                    {
                        "bl_idname": "NodeSocketVector",
                        "default_value": [
                            0.0,
                            0.0,
                            0.0
                        ],
                        "index": 2
                    },
                    {
                        "bl_idname": "NodeSocketFloat",
                        "default_value": 1.0,
                        "index": 3
                    }
                ],
                "outputs": [
                    {
                        "bl_idname": "NodeSocketVector",
                        "default_value": [
                            0.0,
                            0.0,
                            0.0
                        ],
                        "to_socket_index": [
                            0
                        ],
                        "to_node": [
                            "Group Output"
                        ],
                        "index": 0
                    }
                ]
            },
            "Vector Math.007": {
                "bl_idname": "ShaderNodeVectorMath",
                "location": [
                    389.698974609375,
                    -144.93312072753906
                ],
                "name": "Vector Math.007",
                "operation": "NORMALIZE",
                "inputs": [
                    {
                        "bl_idname": "NodeSocketVector",
                        "default_value": [
                            0.0,
                            0.0,
                            0.0
                        ],
                        "index": 0
                    },
                    {
                        "bl_idname": "NodeSocketVector",
                        "default_value": [
                            0.0,
                            0.0,
                            0.0
                        ],
                        "index": 1
                    },
                    {
                        "bl_idname": "NodeSocketVector",
                        "default_value": [
                            0.0,
                            0.0,
                            0.0
                        ],
                        "index": 2
                    },
                    {
                        "bl_idname": "NodeSocketFloat",
                        "default_value": 1.0,
                        "index": 3
                    }
                ],
                "outputs": [
                    {
                        "bl_idname": "NodeSocketVector",
                        "default_value": [
                            0.0,
                            0.0,
                            0.0
                        ],
                        "to_socket_index": [
                            1
                        ],
                        "to_node": [
                            "Group Output"
                        ],
                        "index": 0
                    }
                ]
            }
        },
        "interface_items": [
            {
                "name": "Previous Edge",
                "in_out": "OUTPUT",
                "socket_type": "NodeSocketVector",
                "default_value": [
                    0.0,
                    0.0,
                    0.0
                ],
                "dimensions": 3,
                "max_value": 3.4028234663852886e+38,
                "subtype": "NONE",
                "bl_idname": "NodeTreeInterfaceSocketVector"
            },
            {
                "name": "Next Edge",
                "in_out": "OUTPUT",
                "socket_type": "NodeSocketVector",
                "default_value": [
                    0.0,
                    0.0,
                    0.0
                ],
                "dimensions": 3,
                "max_value": 3.4028234663852886e+38,
                "subtype": "NONE",
                "bl_idname": "NodeTreeInterfaceSocketVector"
            },
            {
                "name": "Geometry",
                "socket_type": "NodeSocketGeometry",
                "bl_idname": "NodeTreeInterfaceSocketGeometry"
            },
            {
                "name": "Index",
                "socket_type": "NodeSocketInt",
                "subtype": "NONE",
                "bl_idname": "NodeTreeInterfaceSocketInt"
            }
        ]
    },
    "blender_version": "4.5.0",
    "tree_type": "GeometryNodeTree",
    "category": "Groups"
}