{
    "name": "Mesh Has Height Of Zero",
    "tree": {
        "bl_idname": "GeometryNodeTree",
        "color_tag": "INPUT",
        "name": "Mesh Has Height Of Zero",
        "uuid": "e5b9fa21-5521-4d82-b7fe-1a1885ecbc0e",
        "nodes": {
            "Group Output": {
                "bl_idname": "NodeGroupOutput",
                "location": [
                    364.8280029296875,
                    -41.97321319580078
                ],
                "name": "Group Output"
            },
            "Group Input": {
                "bl_idname": "NodeGroupInput",
                "location": [
                    -364.2412414550781,
                    -37.25636291503906
                ],
                "name": "Group Input",
                "outputs": [
                    {
                        "bl_idname": "NodeSocketGeometry",
                        "to_socket_index": [
                            0
                        ],
                        "to_node": [
                            "Group"
                        ],
                        "index": 0
                    }
                ]
            },
            "Compare": {
                "bl_idname": "FunctionNodeCompare",
                "location": [
                    113.89216613769531,
                    66.59563446044922
                ],
                "name": "Compare",
                "inputs": [
                    {
                        "bl_idname": "NodeSocketVector",
                        "default_value": [
                            0.0,
                            0.0,
                            0.0
                        ],
                        "index": 4
                    },
                    {
                        "bl_idname": "NodeSocketVector",
                        "default_value": [
                            0.0,
                            0.0,
                            0.0
                        ],
                        "index": 5
                    },
                    {
                        "bl_idname": "NodeSocketColor",
                        "default_value": [
                            0.800000011920929,
                            0.800000011920929,
                            0.800000011920929,
                            1.0
                        ],
                        "index": 6
                    },
                    {
                        "bl_idname": "NodeSocketColor",
                        "default_value": [
                            0.800000011920929,
                            0.800000011920929,
                            0.800000011920929,
                            1.0
                        ],
                        "index": 7
                    },
                    {
                        "bl_idname": "NodeSocketFloat",
                        "default_value": 0.8999999761581421,
                        "index": 10
                    },
                    {
                        "bl_idname": "NodeSocketFloatAngle",
                        "default_value": 0.08726649731397629,
                        "index": 11
                    },
                    {
                        "bl_idname": "NodeSocketFloat",
                        "default_value": 0.0010000000474974513,
                        "index": 12
                    }
                ],
                "outputs": [
                    {
                        "bl_idname": "NodeSocketBool",
                        "to_socket_index": [
                            0
                        ],
                        "to_node": [
                            "Group Output"
                        ],
                        "index": 0
                    }
                ]
            },
            "Group": {
                "bl_idname": "GeometryNodeGroup",
                "location": [
                    -114.47892761230469,
                    12.633943557739258
                ],
                "name": "Group",
                "node_tree": "e56e3eff-42ce-4cda-a154-9dde2ccf6353",
                "outputs": [
                    {
                        "bl_idname": "NodeSocketFloat",
                        "to_socket_index": [
                            0
                        ],
                        "to_node": [
                            "Compare"
                        ],
                        "index": 0
                    }
                ]
            }
        },
        "interface_items": [
            {
                "name": "Result",
                "in_out": "OUTPUT",
                "socket_type": "NodeSocketBool",
                "bl_idname": "NodeTreeInterfaceSocketBool"
            },
            {
                "name": "Geometry",
                "socket_type": "NodeSocketGeometry",
                "bl_idname": "NodeTreeInterfaceSocketGeometry"
            }
        ]
    },
    "blender_version": "4.5.0",
    "tree_type": "GeometryNodeTree",
    "category": "Groups"
}